{"cameraMode":{"drawMode":0,"name":"Shaded","section":"Shading Mode"},"sceneLighting":true,"audioPlay":false,"sceneViewState":{"m_AlwaysRefresh":false,"showFog":true,"showSkybox":true,"showFlares":true,"showImageEffects":true,"showParticleSystems":true,"showVisualEffectGraphs":true,"m_FxEnabled":true},"in2DMode":false,"pivot":{"x":-3.9193506240844728,"y":-2.0822014808654787,"z":14.975188255310059},"rotation":{"x":-0.28615835309028628,"y":-0.45264795422554018,"z":0.15542417764663697,"w":-0.8296831846237183},"size":13.462313652038575,"orthographic":false}